dbt_column_lineage/__init__.py
dbt_column_lineage/_version.py
dbt_column_lineage/constants.py
dbt_column_lineage/lineage.py
dbt_column_lineage/looker.py
dbt_column_lineage/main.py
dbt_column_lineage/utils.py
dbt_column_lineage/frontend_out/404.html
dbt_column_lineage/frontend_out/cl.html
dbt_column_lineage/frontend_out/cl.txt
dbt_column_lineage/frontend_out/cte.html
dbt_column_lineage/frontend_out/cte.txt
dbt_column_lineage/frontend_out/favicon.ico
dbt_column_lineage/frontend_out/index.html
dbt_column_lineage/frontend_out/index.txt
dbt_column_lineage/frontend_out/login.html
dbt_column_lineage/frontend_out/login.txt
dbt_column_lineage/frontend_out/next.svg
dbt_column_lineage/frontend_out/vercel.svg
dbt_column_lineage/frontend_out/_next/static/ODpPp9atTrc9rbAR57m9j/_buildManifest.js
dbt_column_lineage/frontend_out/_next/static/ODpPp9atTrc9rbAR57m9j/_ssgManifest.js
dbt_column_lineage/frontend_out/_next/static/chunks/11-e4abc14c7cfbe5c4.js
dbt_column_lineage/frontend_out/_next/static/chunks/117-e22ff13bb8a9ba3e.js
dbt_column_lineage/frontend_out/_next/static/chunks/363642f4-ec1c8f7ada5abae3.js
dbt_column_lineage/frontend_out/_next/static/chunks/496-e8e78466a9bad7b7.js
dbt_column_lineage/frontend_out/_next/static/chunks/563-ba4f44ac75136d88.js
dbt_column_lineage/frontend_out/_next/static/chunks/848-aef447d17d5415dd.js
dbt_column_lineage/frontend_out/_next/static/chunks/870fdd6f-5a025ee06d6e9571.js
dbt_column_lineage/frontend_out/_next/static/chunks/c37d3baf-73b9054a72453f30.js
dbt_column_lineage/frontend_out/_next/static/chunks/fd9d1056-e7bd7d36e9f974f9.js
dbt_column_lineage/frontend_out/_next/static/chunks/framework-b370f160bb96059c.js
dbt_column_lineage/frontend_out/_next/static/chunks/main-app-aa9ef321b419b108.js
dbt_column_lineage/frontend_out/_next/static/chunks/main-cd3d8f4f5066581c.js
dbt_column_lineage/frontend_out/_next/static/chunks/polyfills-42372ed130431b0a.js
dbt_column_lineage/frontend_out/_next/static/chunks/webpack-27e4049e4a9999e7.js
dbt_column_lineage-0.5.26.dist-info/METADATA
dbt_column_lineage-0.5.26.dist-info/WHEEL
dbt_column_lineage-0.5.26.dist-info/entry_points.txt
dbt_column_lineage-0.5.26.dist-info/top_level.txt
dbt_column_lineage-0.5.26.dist-info/RECORD
