Metadata-Version: 2.1
Name: dbt_column_lineage
Version: 0.5.26
Summary: A tool for dbt column lineage
Author-email: Tomoki Takahashi <takahashi_tomoki@oisixradaichi.co.jp>
Project-URL: Repository, https://github.com/tomoki-takahashi-oisix/dbt-column-lineage
Classifier: Programming Language :: Python :: 3.11
Classifier: Programming Language :: Python :: 3.12
Classifier: License :: OSI Approved :: MIT License
Classifier: Operating System :: OS Independent
Requires-Python: >=3.11
Provides-Extra: dev
Requires-Dist: pytest ; extra == 'dev'
Requires-Dist: black ; extra == 'dev'
Requires-Dist: isort ; extra == 'dev'
